webshell/__init__.py
webshell/static/index.css
webshell/templates/form.html
webshell-0.0.3.dist-info/METADATA
webshell-0.0.3.dist-info/WHEEL
webshell-0.0.3.dist-info/top_level.txt
webshell-0.0.3.dist-info/RECORD
