Metadata-Version: 2.1
Name: webshell
Version: 0.0.3
Summary: A Python package to add web ui on command line application
Home-page: https://gitlab.midwestholding.dev/programmers.io/web_shell
Author: Manoj Datt
Author-email: manoj.datt@programmers.io
License: BSD 2-clause
Platform: any
Classifier: Development Status :: 1 - Planning
Classifier: Intended Audience :: Science/Research
Classifier: License :: OSI Approved :: BSD License
Classifier: Operating System :: POSIX :: Linux
Classifier: Programming Language :: Python :: 3.5
Classifier: Programming Language :: Python :: 3.7
Classifier: Programming Language :: Python :: 3.8
Requires-Dist: Flask (==2.0.2)
Requires-Dist: pypandoc (==1.6.4)
